quorus/cli/__init__.py
quorus/cli/ibm_hardware_runs.py
quorus/cli/qfl_main_test.py
quorus/cli/qfl_main_test_base.py
quorus/data_ops/__init__.py
quorus/data_ops/data_loading.py
quorus/data_ops/data_loading_wrapper.py
quorus/data_ops/data_processing.py
quorus/factory_funcs/__init__.py
quorus/factory_funcs/patchquantumgen_factory.py
quorus/factory_funcs/pca_discriminator_factory.py
quorus/factory_funcs/pca_rescaler_factory.py
quorus/factory_funcs/variationalquantumclassif_factory.py
quorus/logging/__init__.py
quorus/logging/custom_slog.py
quorus/metrics_funcs/__init__.py
quorus/metrics_funcs/acc_funcs/__init__.py
quorus/metrics_funcs/acc_funcs/accuracy_func.py
quorus/metrics_funcs/acc_funcs/accuracy_stddev_func.py
quorus/metrics_funcs/acc_funcs/topk_accuracy_func.py
quorus/metrics_funcs/agg_metrics_func/__init__.py
quorus/metrics_funcs/agg_metrics_func/agg_metrics_func_eval.py
quorus/metrics_funcs/fid_funcs/__init__.py
quorus/metrics_funcs/fid_funcs/compute_fid.py
quorus/metrics_funcs/pennylane_lossfns/__init__.py
quorus/metrics_funcs/pennylane_lossfns/pennylane_lossfn.py
quorus/metrics_funcs/pennylane_lossfns/pennylane_lossfn_batch.py
quorus/metrics_funcs/torch_lossfns/__init__.py
quorus/metrics_funcs/torch_lossfns/klloss.py
quorus/misc_utils/__init__.py
quorus/misc_utils/convert_data_to_lib.py
quorus/misc_utils/count_numcli_clitype.py
quorus/misc_utils/count_qubits_layers.py
quorus/misc_utils/create_feat_list_expansion_data.py
quorus/misc_utils/reorder_amplitude_data.py
quorus/param_processing/__init__.py
quorus/param_processing/numpy_funcs/__init__.py
quorus/param_processing/numpy_funcs/param_comparison.py
quorus/param_processing/numpy_funcs/param_grads_utils_pennylane.py
quorus/param_processing/torch_funcs/__init__.py
quorus/param_processing/torch_funcs/state_dict_diffs.py
quorus/parameter_initialization/__init__.py
quorus/parameter_initialization/identity_init_utils/__init__.py
quorus/parameter_initialization/identity_init_utils/id_init_func.py
quorus-0.1.0.dist-info/licenses/LICENSE
quorus-0.1.0.dist-info/METADATA
quorus-0.1.0.dist-info/WHEEL
quorus-0.1.0.dist-info/entry_points.txt
quorus-0.1.0.dist-info/top_level.txt
quorus-0.1.0.dist-info/RECORD
