Metadata-Version: 2.4
Name: quorus
Version: 0.1.0
Summary: A framework for quantum federated learning across heterogeneous quantum clients
Author-email: Positive Technology Lab <info@positivetechnologylab.com>
License: MIT License
Project-URL: Homepage, https://github.com/positivetechnologylab/Quorus
Project-URL: Repository, https://github.com/positivetechnologylab/Quorus
Project-URL: Issues, https://github.com/positivetechnologylab/Quorus/issues
Project-URL: Documentation, https://github.com/positivetechnologylab/Quorus#readme
Keywords: quantum,federated-learning,qml,pennylane,qiskit,pytorch
Classifier: Development Status :: 3 - Alpha
Classifier: Intended Audience :: Science/Research
Classifier: License :: OSI Approved :: MIT License
Classifier: Programming Language :: Python
Classifier: Programming Language :: Python :: 3
Classifier: Programming Language :: Python :: 3.12
Classifier: Programming Language :: Python :: 3.13
Classifier: Operating System :: OS Independent
Classifier: Topic :: Scientific/Engineering :: Artificial Intelligence
Requires-Python: >=3.12
License-File: LICENSE
Requires-Dist: numpy>=1.26
Requires-Dist: scipy>=1.11
Requires-Dist: pandas>=2.0
Requires-Dist: scikit-learn>=1.3
Requires-Dist: matplotlib>=3.7
Requires-Dist: rich>=13.0
Requires-Dist: pennylane>=0.42
Requires-Dist: pennylane-lightning>=0.42
Requires-Dist: qiskit>=2.0
Requires-Dist: torch>=2.2
Requires-Dist: torchvision>=0.17
Requires-Dist: pytorch-fid>=0.3
Provides-Extra: hardware
Requires-Dist: amazon-braket-sdk>=1.90; extra == "hardware"
Requires-Dist: amazon-braket-schemas>=1.21; extra == "hardware"
Requires-Dist: amazon-braket-default-simulator>=1.12; extra == "hardware"
Requires-Dist: amazon-braket-pennylane-plugin>=1.26; extra == "hardware"
Requires-Dist: qiskit-aer>=0.13; extra == "hardware"
Requires-Dist: qiskit-ibm-runtime>=0.22; extra == "hardware"
Requires-Dist: python-dotenv>=1.0; extra == "hardware"
Requires-Dist: requests>=2.32; extra == "hardware"
Dynamic: license-file
